PythonFireFx/FireFx.c
PythonFireFx/FireFx.cp310-win_amd64.pyd
PythonFireFx/FireFx.pxd
PythonFireFx/FireFx.pyx
PythonFireFx/__init__.pxd
PythonFireFx/__init__.py
PythonFireFx/demo_fire.py
PythonFireFx/setup_FireFx.py
PythonFireFx/Assets/Fire.jpg
PythonFireFx/Assets/FireImage.PNG
PythonFireFx/Assets/background.jpg
PythonFireFx/Assets/firepit.wav
PythonFireFx/Doc/doctrees/environment.pickle
PythonFireFx/Doc/doctrees/index.doctree
PythonFireFx/Doc/html/.buildinfo
PythonFireFx/Doc/html/genindex.html
PythonFireFx/Doc/html/index.html
PythonFireFx/Doc/html/index.html.bak
PythonFireFx/Doc/html/objects.inv
PythonFireFx/Doc/html/search.html
PythonFireFx/Doc/html/searchindex.js
PythonFireFx/Doc/html/_sources/index.rst.txt
PythonFireFx/Doc/html/_static/agogo.css
PythonFireFx/Doc/html/_static/basic.css
PythonFireFx/Doc/html/_static/bgfooter.png
PythonFireFx/Doc/html/_static/bgtop.png
PythonFireFx/Doc/html/_static/doctools.js
PythonFireFx/Doc/html/_static/documentation_options.js
PythonFireFx/Doc/html/_static/file.png
PythonFireFx/Doc/html/_static/jquery-3.5.1.js
PythonFireFx/Doc/html/_static/jquery.js
PythonFireFx/Doc/html/_static/language_data.js
PythonFireFx/Doc/html/_static/minus.png
PythonFireFx/Doc/html/_static/plus.png
PythonFireFx/Doc/html/_static/pygments.css
PythonFireFx/Doc/html/_static/searchtools.js
PythonFireFx/Doc/html/_static/underscore-1.13.1.js
PythonFireFx/Doc/html/_static/underscore.js
PythonFireFx/Include/ShaderLib.c
PythonFireFx/__pycache__/__init__.cpython-38.pyc
PythonFireFx-1.0.0.data/data/lib/site-packages/PythonFireFx/FireFx.pxd
PythonFireFx-1.0.0.data/data/lib/site-packages/PythonFireFx/FireFx.pyx
PythonFireFx-1.0.0.data/data/lib/site-packages/PythonFireFx/LICENSE
PythonFireFx-1.0.0.data/data/lib/site-packages/PythonFireFx/MANIFEST.in
PythonFireFx-1.0.0.data/data/lib/site-packages/PythonFireFx/README.md
PythonFireFx-1.0.0.data/data/lib/site-packages/PythonFireFx/__init__.pxd
PythonFireFx-1.0.0.data/data/lib/site-packages/PythonFireFx/__init__.py
PythonFireFx-1.0.0.dist-info/LICENSE
PythonFireFx-1.0.0.dist-info/METADATA
PythonFireFx-1.0.0.dist-info/WHEEL
PythonFireFx-1.0.0.dist-info/top_level.txt
PythonFireFx-1.0.0.dist-info/RECORD
