Metadata-Version: 2.1
Name: PythonFireFx
Version: 1.0.0
Summary: Python procedural fire effect
Home-page: https://github.com/yoyoberenguer/PythonFireFx
Author: Yoann Berenguer
Author-email: yoyoberenguer@hotmail.com
License: GNU General Public License v3.0
Project-URL: Bug Reports, https://github.com/yoyoberenguer/PythonFireFx/issues
Project-URL: Source, https://github.com/yoyoberenguer/PythonFireFx
Platform: Windows
Classifier: Development Status :: 4 - Beta
Classifier: Intended Audience :: Developers
Classifier: Topic :: Software Development :: Build Tools
Classifier: Operating System :: Microsoft :: Windows
Classifier: Programming Language :: Python
Classifier: Programming Language :: Cython
Classifier: License :: OSI Approved :: GNU General Public License v3 (GPLv3)
Classifier: Programming Language :: Python :: 3.6
Classifier: Programming Language :: Python :: 3.7
Classifier: Programming Language :: Python :: 3.8
Classifier: Programming Language :: Python :: 3.9
Classifier: Programming Language :: Python :: 3.10
Classifier: Topic :: Software Development :: Libraries :: Python Modules
Requires-Python: >=3.6
License-File: LICENSE
